MANIFEST.in
README.rst
setup.py
cloudprinting/__init__.py
cloudprinting/__main__.py
cloudprinting/auth.py
cloudprinting/client.py
cloudprinting/sample.py
cloudprinting.egg-info/PKG-INFO
cloudprinting.egg-info/SOURCES.txt
cloudprinting.egg-info/dependency_links.txt
cloudprinting.egg-info/requires.txt
cloudprinting.egg-info/top_level.txt