Metadata-Version: 1.1
Name: cloudprinting
Version: 0.3.1
Summary: Simple API for Google Cloud Print
Home-page: http://pypi.python.org/pypi/cloudprinting/
Author: Bradley Ayers
Author-email: bradley.ayers@gmail.com
License: UNKNOWN
Platform: UNKNOWN
Classifier: Environment :: Web Environment
Classifier: Intended Audience :: Developers
Classifier: Operating System :: OS Independent
Classifier: Programming Language :: Python
Classifier: Topic :: Internet
Classifier: Topic :: Software Development :: Libraries
